README.md
setup.cfg
setup.py
pyarkbench/__init__.py
pyarkbench/benchmarking_utils.py
pyarkbench/runner_utils.py
pyarkbench.egg-info/PKG-INFO
pyarkbench.egg-info/SOURCES.txt
pyarkbench.egg-info/dependency_links.txt
pyarkbench.egg-info/not-zip-safe
pyarkbench.egg-info/top_level.txt