Metadata-Version: 2.1
Name: pyarkbench
Version: 1.0.1
Summary: Benchmarking utilities
Home-page: http://github.com/driazati/pyarkbench
Author: driazati
License: MIT
Platform: UNKNOWN
